odoo/addons/account_mass_reconcile_by_purchase_line/README.rst
odoo/addons/account_mass_reconcile_by_purchase_line/__init__.py
odoo/addons/account_mass_reconcile_by_purchase_line/__manifest__.py
odoo/addons/account_mass_reconcile_by_purchase_line/i18n/account_mass_reconcile_by_purchase_line.pot
odoo/addons/account_mass_reconcile_by_purchase_line/i18n/ar.po
odoo/addons/account_mass_reconcile_by_purchase_line/i18n/es.po
odoo/addons/account_mass_reconcile_by_purchase_line/models/__init__.py
odoo/addons/account_mass_reconcile_by_purchase_line/models/advanced_reconciliation.py
odoo/addons/account_mass_reconcile_by_purchase_line/models/base_advanced_reconciliation.py
odoo/addons/account_mass_reconcile_by_purchase_line/models/mass_reconcile.py
odoo/addons/account_mass_reconcile_by_purchase_line/readme/CONTRIBUTORS.rst
odoo/addons/account_mass_reconcile_by_purchase_line/readme/DESCRIPTION.rst
odoo/addons/account_mass_reconcile_by_purchase_line/readme/USAGE.rst
odoo/addons/account_mass_reconcile_by_purchase_line/security/ir.model.access.csv
odoo/addons/account_mass_reconcile_by_purchase_line/static/description/icon.png
odoo/addons/account_mass_reconcile_by_purchase_line/static/description/index.html
odoo/addons/account_mass_reconcile_by_purchase_line/views/mass_reconcile.xml
odoo_addon_account_mass_reconcile_by_purchase_line-15.0.1.0.0.4.dist-info/METADATA
odoo_addon_account_mass_reconcile_by_purchase_line-15.0.1.0.0.4.dist-info/WHEEL
odoo_addon_account_mass_reconcile_by_purchase_line-15.0.1.0.0.4.dist-info/top_level.txt
odoo_addon_account_mass_reconcile_by_purchase_line-15.0.1.0.0.4.dist-info/RECORD
