Metadata-Version: 2.1
Name: odoo-addon-account-mass-reconcile-by-purchase-line
Version: 15.0.1.0.0.4
Summary: Allows to reconcile based on the PO line
Home-page: https://github.com/OCA/account-reconcile
Author: ForgeFlow, Odoo Community Association (OCA)
Author-email: support@odoo-community.org
License: AGPL-3
Platform: UNKNOWN
Classifier: Programming Language :: Python
Classifier: Framework :: Odoo
Classifier: Framework :: Odoo :: 15.0
Classifier: License :: OSI Approved :: GNU Affero General Public License v3
Requires-Python: >=3.8
Requires-Dist: odoo-addon-account-mass-reconcile <15.1dev,>=15.0dev
Requires-Dist: odoo-addon-account-move-line-purchase-info <15.1dev,>=15.0dev
Requires-Dist: odoo <15.1dev,>=15.0a
